civitai_comfy_nodes/.gitignore
civitai_comfy_nodes/CivitAI_Model.py
civitai_comfy_nodes/__init__.py
civitai_comfy_nodes/civitai_checkpoint_loader.py
civitai_comfy_nodes/civitai_lora_loader.py
civitai_comfy_nodes/pyproject.toml
civitai_comfy_nodes/utils.py
civitai_comfy_nodes-0.2.0.dist-info/METADATA
civitai_comfy_nodes-0.2.0.dist-info/WHEEL
civitai_comfy_nodes-0.2.0.dist-info/entry_points.txt
civitai_comfy_nodes-0.2.0.dist-info/RECORD
