Metadata-Version: 2.1
Name: civitai_comfy_nodes
Version: 0.2.0
Project-URL: Homepage, https://github.com/Chaoses-Ib/civitai_comfy_nodes
Project-URL: comfyui-legacy, https://github.com/Chaoses-Ib/comfyui-legacy
Keywords: comfyui
